izviz/__init__.py
izviz/viz.py
izviz-0.1.dist-info/METADATA
izviz-0.1.dist-info/WHEEL
izviz-0.1.dist-info/top_level.txt
izviz-0.1.dist-info/RECORD
